[
  {
    "fecha": "2026-01-01",
    "descripcion": "Feria judicial de Enero"
  },
  {
    "fecha": "2026-01-02",
    "descripcion": "Feria judicial de Enero"
  },

  {
    "fecha": "2026-01-03",
    "descripcion": "Feria judicial de Enero"
  },
  {
    "fecha": "2026-01-04",
    "descripcion": "Feria judicial de Enero"
  },
  {
    "fecha": "2026-01-05",
    "descripcion": "Feria judicial de Enero"
  },
  {
    "fecha": "2026-01-06",
    "descripcion": "Feria judicial de Enero"
  },
  {
    "fecha": "2026-01-07",
    "descripcion": "Feria judicial de Enero"
  },
  {
    "fecha": "2026-01-08",
    "descripcion": "Feria judicial de Enero"
  },
  {
    "fecha": "2026-01-09",
    "descripcion": "Feria judicial de Enero"
  },
  {
    "fecha": "2026-01-10",
    "descripcion": "Feria judicial de Enero"
  },
  {
    "fecha": "2026-01-11",
    "descripcion": "Feria judicial de Enero"
  },
  {
    "fecha": "2026-01-12",
    "descripcion": "Feria judicial de Enero"
  },
  {
    "fecha": "2026-01-13",
    "descripcion": "Feria judicial de Enero"
  },
  {
    "fecha": "2026-01-14",
    "descripcion": "Feria judicial de Enero"
  },
  {
    "fecha": "2026-01-15",
    "descripcion": "Feria judicial de Enero"
  },
  {
    "fecha": "2026-01-16",
    "descripcion": "Feria judicial de Enero"
  },
  {
    "fecha": "2026-01-17",
    "descripcion": "Feria judicial de Enero"
  },
  {
    "fecha": "2026-01-18",
    "descripcion": "Feria judicial de Enero"
  },
  {
    "fecha": "2026-01-19",
    "descripcion": "Feria judicial de Enero"
  },
  {
    "fecha": "2026-01-20",
    "descripcion": "Feria judicial de Enero"
  },
  {
    "fecha": "2026-01-21",
    "descripcion": "Feria judicial de Enero"
  },
  {
    "fecha": "2026-01-22",
    "descripcion": "Feria judicial de Enero"
  },
  {
    "fecha": "2026-01-23",
    "descripcion": "Feria judicial de Enero"
  },
  {
    "fecha": "2026-01-24",
    "descripcion": "Feria judicial de Enero"
  },
  {
    "fecha": "2026-01-25",
    "descripcion": "Feria judicial de Enero"
  },
  {
    "fecha": "2026-01-26",
    "descripcion": "Feria judicial de Enero"
  },
  {
    "fecha": "2026-01-27",
    "descripcion": "Feria judicial de Enero"
  },
  {
    "fecha": "2026-01-28",
    "descripcion": "Feria judicial de Enero"
  },
  {
    "fecha": "2026-01-29",
    "descripcion": "Feria judicial de Enero"
  },
  {
    "fecha": "2026-01-30",
    "descripcion": "Feria judicial de Enero"
  },
  {
    "fecha": "2026-01-31",
    "descripcion": "Feria judicial de Enero"
  },
  {
    "fecha": "2026-07-20",
    "descripcion": "Feria judicial de Julio"
  },
  {
    "fecha": "2026-07-21",
    "descripcion": "Feria judicial de Julio"
  },
  {
    "fecha": "2026-07-22",
    "descripcion": "Feria judicial de Julio"
  },
  {
    "fecha": "2026-07-23",
    "descripcion": "Feria judicial de Julio"
  },
  {
    "fecha": "2026-07-24",
    "descripcion": "Feria judicial de Julio"
  },
  {
    "fecha": "2026-07-25",
    "descripcion": "Feria judicial de Julio"
  },
  {
    "fecha": "2026-07-26",
    "descripcion": "Feria judicial de Julio"
  },
  {
    "fecha": "2026-07-27",
    "descripcion": "Feria judicial de Julio"
  },
  {
    "fecha": "2026-07-28",
    "descripcion": "Feria judicial de Julio"
  },
  {
    "fecha": "2026-07-29",
    "descripcion": "Feria judicial de Julio"
  },
  {
    "fecha": "2026-07-30",
    "descripcion": "Feria judicial de Julio"
  },
  {
    "fecha": "2026-07-31",
    "descripcion": "Feria judicial de Julio"
  },
  {
    "fecha": "2026-04-21",
    "descripcion": "Inhabil decretado por CSJN - Res 926/2026"
  },
  {
    "fecha": "2026-04-22",
    "descripcion": "Inhabil decretado por CSJN - Res 926/2026"
  }
]
